mmf_meta/__init__.py
mmf_meta/__main__.py
mmf_meta/_imports.py
mmf_meta/autodoc.py
mmf_meta/core.py
mmf_meta/descriptors.py
mmf_meta/df_io.py
mmf_meta/formats.py
mmf_meta-0.1.13.dist-info/entry_points.txt
mmf_meta-0.1.13.dist-info/WHEEL
mmf_meta-0.1.13.dist-info/METADATA
mmf_meta-0.1.13.dist-info/RECORD
