Metadata-Version: 2.1
Name: mmf-meta
Version: 0.1.13
Summary: 
Author: Викторов Андрей Германович
Author-email: andvikt@gmail.com
Requires-Python: >=3.7,<4.0
Classifier: Programming Language :: Python :: 3
Classifier: Programming Language :: Python :: 3.10
Classifier: Programming Language :: Python :: 3.7
Classifier: Programming Language :: Python :: 3.8
Classifier: Programming Language :: Python :: 3.9
Provides-Extra: PyTurboJPEG
Provides-Extra: XlsxWriter
Provides-Extra: opencv-python
Provides-Extra: openpyxl
Provides-Extra: pandas
Provides-Extra: xlrd
Requires-Dist: PyTurboJPEG (>=1.3,<2.0)
Requires-Dist: XlsxWriter (>=3,<4)
Requires-Dist: click (>=8)
Requires-Dist: opencv-python (>=4.1,<5.0)
Requires-Dist: openpyxl (>=3)
Requires-Dist: pandas (>=0.22,<1.4); python_version >= "3.7" and python_version < "4.0"
Requires-Dist: pandas (>=1.4,<2); (python_version >= "3.8" and python_version < "4.0") and (extra == "pandas" or extra == "openpyxl" or extra == "xlrd" or extra == "XlsxWriter")
Requires-Dist: xlrd (>=2)
Project-URL: documentation, https://mm-framework.github.io/docs/
Project-URL: homepage, https://github.com/mm-framework/mmf-meta
